pyregtokenizer/__init__.py
pyregtokenizer/regextokenizer.py
tokenizer/__init__.py
tokenizer/regextokenizer.py
pyregtokenizer-0.0.2.dist-info/METADATA
pyregtokenizer-0.0.2.dist-info/WHEEL
pyregtokenizer-0.0.2.dist-info/top_level.txt
pyregtokenizer-0.0.2.dist-info/RECORD
